{
	"$schema": "https://biomejs.dev/schemas/1.9.4/schema.json",
	"vcs": { "enabled": false, "clientKind": "git", "useIgnoreFile": false },
	"files": { "ignoreUnknown": false, "ignore": [] },
	"formatter": { "enabled": true, "indentStyle": "tab" },
	"organizeImports": { "enabled": true },
	"linter": {
		"enabled": true,
		"rules": {
			"recommended": false,
			"complexity": {
				"noExtraBooleanCast": "error",
				"noMultipleSpacesInRegularExpressionLiterals": "error",
				"noUselessCatch": "error",
				"noUselessConstructor": "error",
				"noUselessLoneBlockStatements": "error",
				"noUselessRename": "error",
				"noUselessTernary": "error",
				"noUselessUndefinedInitialization": "error",
				"noVoid": "error",
				"noWith": "error",
				"useLiteralKeys": "error",
				"useRegexLiterals": "error"
			},
			"correctness": {
				"noConstAssign": "error",
				"noConstantCondition": "error",
				"noEmptyCharacterClassInRegex": "error",
				"noEmptyPattern": "error",
				"noGlobalObjectCalls": "error",
				"noInvalidBuiltinInstantiation": "error",
				"noInvalidConstructorSuper": "error",
				"noInvalidUseBeforeDeclaration": "error",
				"noNewSymbol": "error",
				"noNonoctalDecimalEscape": "error",
				"noPrecisionLoss": "error",
				"noSelfAssign": "error",
				"noSetterReturn": "error",
				"noSwitchDeclarations": "error",
				"noUndeclaredVariables": "error",
				"noUnreachable": "error",
				"noUnreachableSuper": "error",
				"noUnsafeFinally": "error",
				"noUnsafeOptionalChaining": "error",
				"noUnusedLabels": "error",
				"noUnusedPrivateClassMembers": "error",
				"noUnusedVariables": "error",
				"useArrayLiterals": "error",
				"useIsNan": "error",
				"useValidForDirection": "error",
				"useYield": "error"
			},
			"security": { "noGlobalEval": "error" },
			"style": {
				"noCommaOperator": "error",
				"noVar": "warn",
				"noYodaExpression": "error",
				"useBlockStatements": "error",
				"useConsistentBuiltinInstantiation": "error",
				"useConst": "error",
				"useSingleVarDeclarator": "error",
				"useThrowOnlyError": "error"
			},
			"suspicious": {
				"noAssignInExpressions": "error",
				"noAsyncPromiseExecutor": "error",
				"noCatchAssign": "error",
				"noClassAssign": "error",
				"noCompareNegZero": "error",
				"noConfusingLabels": "error",
				"noControlCharactersInRegex": "error",
				"noDebugger": "error",
				"noDoubleEquals": "error",
				"noDuplicateCase": "error",
				"noDuplicateClassMembers": "error",
				"noDuplicateObjectKeys": "error",
				"noDuplicateParameters": "error",
				"noEmptyBlockStatements": "error",
				"noFallthroughSwitchClause": "error",
				"noFunctionAssign": "error",
				"noGlobalAssign": "error",
				"noImportAssign": "error",
				"noMisleadingCharacterClass": "error",
				"noPrototypeBuiltins": "error",
				"noRedeclare": "error",
				"noSelfCompare": "error",
				"noShadowRestrictedNames": "error",
				"noSparseArray": "error",
				"noUnsafeNegation": "error",
				"useDefaultSwitchClauseLast": "error",
				"useGetterReturn": "error",
				"useValidTypeof": "error"
			}
		},
		"ignore": [
			"build/",
			"build_electron/",
			"electron/plugins/i18n.js",
			"semantic/"
		]
	},
	"javascript": {
		"formatter": { "quoteStyle": "double" },
		"globals": [
			"OffscreenCanvas",
			"onpointerleave",
			"onpointerenter",
			"onemptied",
			"onmouseenter",
			"onkeypress",
			"onloadeddata",
			"window",
			"oninvalid",
			"onmouseup",
			"onvolumechange",
			"onpointerout",
			"onstorage",
			"onpause",
			"onkeyup",
			"onabort",
			"onanimationstart",
			"onafterprint",
			"onblur",
			"ondurationchange",
			"onwaiting",
			"ondeviceorientation",
			"oncanplaythrough",
			"onclose",
			"onbeforeunload",
			"onanimationend",
			"onmouseleave",
			"oncancel",
			"onseeked",
			"onpointerover",
			"ondragleave",
			"ongotpointercapture",
			"onloadedmetadata",
			"onpageshow",
			"onplay",
			"document",
			"onunhandledrejection",
			"onbeforeprint",
			"onstalled",
			"oncontextmenu",
			"onreset",
			"onpointercancel",
			"onsubmit",
			"ondrag",
			"onload",
			"onlostpointercapture",
			"onsuspend",
			"ondragstart",
			"onpagehide",
			"onmessage",
			"location",
			"onoffline",
			"onappinstalled",
			"onrejectionhandled",
			"onunload",
			"onwheel",
			"onended",
			"onmousedown",
			"onpointerup",
			"onmouseover",
			"onkeydown",
			"onclick",
			"onfocus",
			"navigator",
			"onscroll",
			"onresize",
			"onsearch",
			"ontoggle",
			"exports",
			"oncanplay",
			"onlanguagechange",
			"onpointerdown",
			"ondeviceorientationabsolute",
			"ondragenter",
			"onauxclick",
			"onerror",
			"onpointermove",
			"onmousemove",
			"ondevicemotion",
			"ondrop",
			"onhashchange",
			"onanimationiteration",
			"ondblclick",
			"onratechange",
			"ontransitionend",
			"ondragend",
			"onpopstate",
			"onplaying",
			"onchange",
			"onselect",
			"onbeforeinstallprompt",
			"onmouseout",
			"ontimeupdate",
			"ondragover",
			"oncuechange",
			"onprogress",
			"onloadstart",
			"onseeking",
			"oninput",
			"onmessageerror",
			"onmousewheel",
			"ononline"
		]
	},
	"overrides": [
		{
			"include": ["*.vue", "**/*.vue"],
			"javascript": {
				"globals": [
					"OffscreenCanvas",
					"onpointerleave",
					"onpointerenter",
					"onemptied",
					"onmouseenter",
					"onkeypress",
					"onloadeddata",
					"oninvalid",
					"onmouseup",
					"onvolumechange",
					"onpointerout",
					"onstorage",
					"onpause",
					"onkeyup",
					"onabort",
					"onanimationstart",
					"onafterprint",
					"onblur",
					"ondurationchange",
					"onwaiting",
					"ondeviceorientation",
					"oncanplaythrough",
					"onclose",
					"onbeforeunload",
					"onanimationend",
					"onmouseleave",
					"oncancel",
					"onseeked",
					"onpointerover",
					"ondragleave",
					"ongotpointercapture",
					"onloadedmetadata",
					"onpageshow",
					"onplay",
					"onunhandledrejection",
					"onbeforeprint",
					"onstalled",
					"oncontextmenu",
					"onreset",
					"onpointercancel",
					"onsubmit",
					"ondrag",
					"onload",
					"onlostpointercapture",
					"onsuspend",
					"ondragstart",
					"onpagehide",
					"onmessage",
					"location",
					"onoffline",
					"onappinstalled",
					"onrejectionhandled",
					"onunload",
					"onwheel",
					"onended",
					"onmousedown",
					"onpointerup",
					"onmouseover",
					"onkeydown",
					"onclick",
					"onfocus",
					"onscroll",
					"onresize",
					"onsearch",
					"ontoggle",
					"oncanplay",
					"onlanguagechange",
					"onpointerdown",
					"ondeviceorientationabsolute",
					"ondragenter",
					"onauxclick",
					"onerror",
					"onpointermove",
					"onmousemove",
					"ondevicemotion",
					"ondrop",
					"onhashchange",
					"onanimationiteration",
					"ondblclick",
					"onratechange",
					"ontransitionend",
					"ondragend",
					"onpopstate",
					"onplaying",
					"onchange",
					"onselect",
					"onbeforeinstallprompt",
					"onmouseout",
					"ontimeupdate",
					"ondragover",
					"oncuechange",
					"onprogress",
					"onloadstart",
					"onseeking",
					"oninput",
					"onmessageerror",
					"onmousewheel",
					"ononline"
				]
			},
			"linter": { "rules": {} }
		},
		{
			"include": ["**/*.js", "**/*.vue"],
			"javascript": { "globals": [] },
			"linter": {
				"rules": { "correctness": { "noUndeclaredVariables": "off" } }
			}
		},
		{
			"include": ["electron/**/*", "vite.config.mjs"],
			"linter": {
				"rules": { "correctness": { "noUndeclaredVariables": "off" } }
			}
		},
		{
			"include": ["*.vue", "**/*.vue"],
			"javascript": {
				"globals": [
					"OffscreenCanvas",
					"onpointerleave",
					"onpointerenter",
					"onemptied",
					"onmouseenter",
					"onkeypress",
					"onloadeddata",
					"oninvalid",
					"onmouseup",
					"onvolumechange",
					"onpointerout",
					"onstorage",
					"onpause",
					"onkeyup",
					"onabort",
					"onanimationstart",
					"onafterprint",
					"onblur",
					"ondurationchange",
					"onwaiting",
					"ondeviceorientation",
					"oncanplaythrough",
					"onclose",
					"onbeforeunload",
					"onanimationend",
					"onmouseleave",
					"oncancel",
					"onseeked",
					"onpointerover",
					"ondragleave",
					"ongotpointercapture",
					"onloadedmetadata",
					"onpageshow",
					"onplay",
					"onunhandledrejection",
					"onbeforeprint",
					"onstalled",
					"oncontextmenu",
					"onreset",
					"onpointercancel",
					"onsubmit",
					"ondrag",
					"onload",
					"onlostpointercapture",
					"onsuspend",
					"ondragstart",
					"onpagehide",
					"onmessage",
					"location",
					"onoffline",
					"onappinstalled",
					"onrejectionhandled",
					"onunload",
					"onwheel",
					"onended",
					"onmousedown",
					"onpointerup",
					"onmouseover",
					"onkeydown",
					"onclick",
					"onfocus",
					"onscroll",
					"onresize",
					"onsearch",
					"ontoggle",
					"oncanplay",
					"onlanguagechange",
					"onpointerdown",
					"ondeviceorientationabsolute",
					"ondragenter",
					"onauxclick",
					"onerror",
					"onpointermove",
					"onmousemove",
					"ondevicemotion",
					"ondrop",
					"onhashchange",
					"onanimationiteration",
					"ondblclick",
					"onratechange",
					"ontransitionend",
					"ondragend",
					"onpopstate",
					"onplaying",
					"onchange",
					"onselect",
					"onbeforeinstallprompt",
					"onmouseout",
					"ontimeupdate",
					"ondragover",
					"oncuechange",
					"onprogress",
					"onloadstart",
					"onseeking",
					"oninput",
					"onmessageerror",
					"onmousewheel",
					"ononline"
				]
			},
			"linter": { "rules": {} }
		},
		{
			"include": ["**/*.js", "**/*.vue"],
			"javascript": { "globals": [] },
			"linter": {
				"rules": { "correctness": { "noUndeclaredVariables": "off" } }
			}
		},
		{
			"include": ["electron/**/*", "vite.config.mjs"],
			"linter": {
				"rules": { "correctness": { "noUndeclaredVariables": "off" } }
			}
		}
	]
}
